YihanResultSaver/YihanResultSaver.py
YihanResultSaver/__init__.py
YihanResultSaver-0.1.1.dist-info/LICENSE
YihanResultSaver-0.1.1.dist-info/METADATA
YihanResultSaver-0.1.1.dist-info/WHEEL
YihanResultSaver-0.1.1.dist-info/top_level.txt
YihanResultSaver-0.1.1.dist-info/RECORD
