Metadata-Version: 2.1
Name: YihanResultSaver
Version: 0.1.1
Summary: A Python decorator for logging, saving results, and tracking function source code.
Home-page: https://github.com/YihanYu115/YihanResultSaver.git
Author: Yihan Yu
Author-email: yihan.yu@iphy.ac.cn
License: MIT
Requires-Python: >=3.6
License-File: LICENSE
Requires-Dist: numpy >=1.21.0
